odoo8_addon_partner_contact_job_position-8.0.1.0.0.99.dev14-py3.8-nspkg.pth
odoo_addons/partner_contact_job_position/README.rst
odoo_addons/partner_contact_job_position/__init__.py
odoo_addons/partner_contact_job_position/__openerp__.py
odoo_addons/partner_contact_job_position/i18n/de.po
odoo_addons/partner_contact_job_position/i18n/es.po
odoo_addons/partner_contact_job_position/i18n/eu.po
odoo_addons/partner_contact_job_position/i18n/fi.po
odoo_addons/partner_contact_job_position/i18n/it.po
odoo_addons/partner_contact_job_position/i18n/partner_contact_job_position.pot
odoo_addons/partner_contact_job_position/i18n/sl.po
odoo_addons/partner_contact_job_position/models/__init__.py
odoo_addons/partner_contact_job_position/models/res_partner.py
odoo_addons/partner_contact_job_position/security/ir.model.access.csv
odoo_addons/partner_contact_job_position/static/description/icon.png
odoo_addons/partner_contact_job_position/views/res_partner_job_position_view.xml
odoo_addons/partner_contact_job_position/views/res_partner_view.xml
odoo8_addon_partner_contact_job_position-8.0.1.0.0.99.dev14.dist-info/METADATA
odoo8_addon_partner_contact_job_position-8.0.1.0.0.99.dev14.dist-info/WHEEL
odoo8_addon_partner_contact_job_position-8.0.1.0.0.99.dev14.dist-info/namespace_packages.txt
odoo8_addon_partner_contact_job_position-8.0.1.0.0.99.dev14.dist-info/top_level.txt
odoo8_addon_partner_contact_job_position-8.0.1.0.0.99.dev14.dist-info/RECORD
